npycentral/__init__.py
npycentral/_version.py
npycentral/client.py
npycentral/exceptions.py
npycentral/mixins/__init__.py
npycentral/mixins/customer_mixin.py
npycentral/mixins/device_mixin.py
npycentral/mixins/filter_mixin.py
npycentral/mixins/property_mixin.py
npycentral/mixins/task_mixin.py
npycentral/models/__init__.py
npycentral/models/active_issue.py
npycentral/models/custom_property.py
npycentral/models/customer.py
npycentral/models/device.py
npycentral/models/device_assets.py
npycentral/models/device_filter.py
npycentral/models/service_monitoring_status.py
npycentral/models/service_organization.py
npycentral-0.1.2.dist-info/METADATA
npycentral-0.1.2.dist-info/WHEEL
npycentral-0.1.2.dist-info/RECORD
