Metadata-Version: 2.4
Name: npycentral
Version: 0.1.2
Summary: Python Toolkit for N-Central RMM API
Project-URL: Homepage, https://github.com/Ruderali/npycentral
Project-URL: Documentation, https://github.com/Ruderali/npycentral/blob/main/docs/api-reference.md
Project-URL: Repository, https://github.com/Ruderali/npycentral
Project-URL: Issues, https://github.com/Ruderali/npycentral/issues
Author-email: Rowan <brookerowan@gmail.com>
License: MIT
Keywords: api,monitoring,n-able,n-central,ncentral,rmm,sdk
Classifier: Development Status :: 4 - Beta
Classifier: Intended Audience :: Developers
Classifier: Intended Audience :: System Administrators
Classifier: License :: OSI Approved :: MIT License
Classifier: Operating System :: OS Independent
Classifier: Programming Language :: Python :: 3
Classifier: Programming Language :: Python :: 3.9
Classifier: Programming Language :: Python :: 3.10
Classifier: Programming Language :: Python :: 3.11
Classifier: Programming Language :: Python :: 3.12
Classifier: Topic :: Software Development :: Libraries :: Python Modules
Classifier: Topic :: System :: Monitoring
Classifier: Topic :: System :: Systems Administration
Requires-Python: >=3.9
Requires-Dist: cachetools>=5.3.0
Requires-Dist: requests>=2.31.0
Provides-Extra: dev
Requires-Dist: black>=23.7.0; extra == 'dev'
Requires-Dist: mypy>=1.5.0; extra == 'dev'
Requires-Dist: pytest-cov>=4.1.0; extra == 'dev'
Requires-Dist: pytest-mock>=3.11.0; extra == 'dev'
Requires-Dist: pytest>=7.4.0; extra == 'dev'
Requires-Dist: responses>=0.23.0; extra == 'dev'
Requires-Dist: ruff>=0.0.285; extra == 'dev'
Requires-Dist: types-cachetools>=5.3.0; extra == 'dev'
Requires-Dist: types-requests>=2.31.0; extra == 'dev'
Provides-Extra: docs
Requires-Dist: mkdocs-material>=9.2.0; extra == 'docs'
Requires-Dist: mkdocs>=1.5.0; extra == 'docs'
Requires-Dist: mkdocstrings[python]>=0.22.0; extra == 'docs'
